pympris-1.4.dist-info/DESCRIPTION.rst
pympris-1.4.dist-info/pydist.json
pympris-1.4.dist-info/RECORD
pympris-1.4.dist-info/METADATA
pympris-1.4.dist-info/top_level.txt
pympris-1.4.dist-info/WHEEL
pympris/__init__.py
pympris/TrackList.py
pympris/Root.py
pympris/PlayLists.py
pympris/Base.py
pympris/Player.py
pympris/MediaPlayer.py
pympris/common.py
