Metadata-Version: 1.1
Name: pympris
Version: 1.4
Summary: Library to control media players using MPRIS2 interfaces
Home-page: https://github.com/wistful/pympris
Author: Mikhail Mamrouski
Author-email: wst.public.mail@gmail.com
License: MIT License
Keywords: mpris,dbus
Platform: Unix,
Classifier: Development Status :: 5 - Production/Stable
Classifier: Environment :: X11 Applications
Classifier: Intended Audience :: Developers
Classifier: License :: OSI Approved :: MIT License
Classifier: Programming Language :: Python :: 2.7
Classifier: Programming Language :: Python :: 3.3
Classifier: Topic :: Software Development :: Libraries :: Python Modules
